awspublicranges/__init__.py
awspublicranges/ranges.py
awspublicranges-1.0.2.dist-info/LICENSE
awspublicranges-1.0.2.dist-info/METADATA
awspublicranges-1.0.2.dist-info/WHEEL
awspublicranges-1.0.2.dist-info/top_level.txt
awspublicranges-1.0.2.dist-info/RECORD
